{
  "generatedAt": "2025-09-27T08:27:17.776Z",
  "results": [
    {
      "url": "http://localhost:3000/founders-letter",
      "label": "founders-letter",
      "styles": {
        "body": {
          "color": "rgb(242, 242, 242)",
          "backgroundColor": "rgb(13, 13, 13)",
          "backgroundImage": "none",
          "fontFamily": "Inter, \"Inter Fallback\"",
          "fontSize": "16px",
          "fontWeight": "400",
          "lineHeight": "24px",
          "letterSpacing": "normal",
          "borderColor": "rgb(51, 51, 51)",
          "borderWidth": "0px",
          "borderStyle": "solid",
          "borderRadius": "0px",
          "boxShadow": "none",
          "colorHex": "#F2F2F2",
          "backgroundColorHex": "#0D0D0D",
          "borderColorHex": "#333333"
        },
        "h1": {
          "color": "rgb(255, 255, 255)",
          "backgroundColor": "rgba(0, 0, 0, 0)",
          "backgroundImage": "none",
          "fontFamily": "Inter, \"Inter Fallback\"",
          "fontSize": "72px",
          "fontWeight": "700",
          "lineHeight": "72px",
          "letterSpacing": "normal",
          "borderColor": "rgb(51, 51, 51)",
          "borderWidth": "0px",
          "borderStyle": "solid",
          "borderRadius": "0px",
          "boxShadow": "none",
          "colorHex": "#FFFFFF",
          "backgroundColorHex": "#000000",
          "borderColorHex": "#333333"
        },
        "h2": {
          "color": "rgb(255, 255, 255)",
          "backgroundColor": "rgba(0, 0, 0, 0)",
          "backgroundImage": "none",
          "fontFamily": "Inter, \"Inter Fallback\"",
          "fontSize": "30px",
          "fontWeight": "700",
          "lineHeight": "36px",
          "letterSpacing": "normal",
          "borderColor": "rgb(51, 51, 51)",
          "borderWidth": "0px",
          "borderStyle": "solid",
          "borderRadius": "0px",
          "boxShadow": "none",
          "colorHex": "#FFFFFF",
          "backgroundColorHex": "#000000",
          "borderColorHex": "#333333"
        },
        "h3": {
          "color": "rgb(251, 146, 60)",
          "backgroundColor": "rgba(0, 0, 0, 0)",
          "backgroundImage": "none",
          "fontFamily": "Inter, \"Inter Fallback\"",
          "fontSize": "20px",
          "fontWeight": "700",
          "lineHeight": "28px",
          "letterSpacing": "normal",
          "borderColor": "rgb(51, 51, 51)",
          "borderWidth": "0px",
          "borderStyle": "solid",
          "borderRadius": "0px",
          "boxShadow": "none",
          "colorHex": "#FB923C",
          "backgroundColorHex": "#000000",
          "borderColorHex": "#333333"
        },
        "p": {
          "color": "rgb(209, 213, 219)",
          "backgroundColor": "rgba(0, 0, 0, 0)",
          "backgroundImage": "none",
          "fontFamily": "Inter, \"Inter Fallback\"",
          "fontSize": "24px",
          "fontWeight": "400",
          "lineHeight": "32px",
          "letterSpacing": "normal",
          "borderColor": "rgb(51, 51, 51)",
          "borderWidth": "0px",
          "borderStyle": "solid",
          "borderRadius": "0px",
          "boxShadow": "none",
          "colorHex": "#D1D5DB",
          "backgroundColorHex": "#000000",
          "borderColorHex": "#333333"
        },
        "a": {
          "color": "rgb(242, 242, 242)",
          "backgroundColor": "rgba(0, 0, 0, 0)",
          "backgroundImage": "none",
          "fontFamily": "Inter, \"Inter Fallback\"",
          "fontSize": "16px",
          "fontWeight": "400",
          "lineHeight": "24px",
          "letterSpacing": "normal",
          "borderColor": "rgb(51, 51, 51)",
          "borderWidth": "0px",
          "borderStyle": "solid",
          "borderRadius": "0px",
          "boxShadow": "none",
          "colorHex": "#F2F2F2",
          "backgroundColorHex": "#000000",
          "borderColorHex": "#333333"
        },
        "button": {
          "color": "rgb(242, 242, 242)",
          "backgroundColor": "rgba(0, 0, 0, 0)",
          "backgroundImage": "none",
          "fontFamily": "Inter, \"Inter Fallback\"",
          "fontSize": "14px",
          "fontWeight": "500",
          "lineHeight": "20px",
          "letterSpacing": "normal",
          "borderColor": "rgb(51, 51, 51)",
          "borderWidth": "0px",
          "borderStyle": "solid",
          "borderRadius": "0px",
          "boxShadow": "none",
          "colorHex": "#F2F2F2",
          "backgroundColorHex": "#000000",
          "borderColorHex": "#333333"
        },
        "nav": {
          "color": "rgb(242, 242, 242)",
          "backgroundColor": "rgba(0, 0, 0, 0)",
          "backgroundImage": "none",
          "fontFamily": "Inter, \"Inter Fallback\"",
          "fontSize": "16px",
          "fontWeight": "400",
          "lineHeight": "24px",
          "letterSpacing": "normal",
          "borderColor": "rgb(51, 51, 51)",
          "borderWidth": "0px",
          "borderStyle": "solid",
          "borderRadius": "0px",
          "boxShadow": "none",
          "colorHex": "#F2F2F2",
          "backgroundColorHex": "#000000",
          "borderColorHex": "#333333"
        },
        "card": {
          "color": "rgb(242, 242, 242)",
          "backgroundColor": "rgb(17, 24, 39)",
          "backgroundImage": "none",
          "fontFamily": "Inter, \"Inter Fallback\"",
          "fontSize": "16px",
          "fontWeight": "400",
          "lineHeight": "24px",
          "letterSpacing": "normal",
          "borderColor": "rgb(31, 41, 55)",
          "borderWidth": "1px",
          "borderStyle": "solid",
          "borderRadius": "12px",
          "boxShadow": "none",
          "colorHex": "#F2F2F2",
          "backgroundColorHex": "#111827",
          "borderColorHex": "#1F2937"
        },
        "brandText": {
          "color": "rgb(249, 116, 21)",
          "backgroundColor": "rgba(0, 0, 0, 0)",
          "backgroundImage": "none",
          "fontFamily": "Inter, \"Inter Fallback\"",
          "fontSize": "20px",
          "fontWeight": "700",
          "lineHeight": "28px",
          "letterSpacing": "normal",
          "borderColor": "rgb(51, 51, 51)",
          "borderWidth": "0px",
          "borderStyle": "solid",
          "borderRadius": "0px",
          "boxShadow": "none",
          "colorHex": "#F97415",
          "backgroundColorHex": "#000000",
          "borderColorHex": "#333333"
        },
        "brandBg": {
          "color": "rgb(242, 242, 242)",
          "backgroundColor": "rgba(249, 115, 22, 0.2)",
          "backgroundImage": "none",
          "fontFamily": "Inter, \"Inter Fallback\"",
          "fontSize": "16px",
          "fontWeight": "400",
          "lineHeight": "24px",
          "letterSpacing": "normal",
          "borderColor": "rgb(249, 115, 22)",
          "borderWidth": "1px",
          "borderStyle": "solid",
          "borderRadius": "8px",
          "boxShadow": "none",
          "colorHex": "#F2F2F2",
          "backgroundColorHex": "#F97316",
          "borderColorHex": "#F97316"
        },
        "gradient": {
          "color": "rgb(242, 242, 242)",
          "backgroundColor": "rgba(0, 0, 0, 0)",
          "backgroundImage": "linear-gradient(to right bottom, rgb(0, 0, 0), rgb(17, 24, 39), rgb(124, 45, 18))",
          "fontFamily": "Inter, \"Inter Fallback\"",
          "fontSize": "16px",
          "fontWeight": "400",
          "lineHeight": "24px",
          "letterSpacing": "normal",
          "borderColor": "rgb(51, 51, 51)",
          "borderWidth": "0px",
          "borderStyle": "solid",
          "borderRadius": "0px",
          "boxShadow": "none",
          "colorHex": "#F2F2F2",
          "backgroundColorHex": "#000000",
          "borderColorHex": "#333333"
        }
      },
      "screenshot": "reports/theme-audit/before/founders-letter.png"
    },
    {
      "url": "http://localhost:3000/why-utah",
      "label": "why-utah",
      "styles": {
        "body": {
          "color": "rgb(242, 242, 242)",
          "backgroundColor": "rgb(13, 13, 13)",
          "backgroundImage": "none",
          "fontFamily": "Inter, \"Inter Fallback\"",
          "fontSize": "16px",
          "fontWeight": "400",
          "lineHeight": "24px",
          "letterSpacing": "normal",
          "borderColor": "rgb(51, 51, 51)",
          "borderWidth": "0px",
          "borderStyle": "solid",
          "borderRadius": "0px",
          "boxShadow": "none",
          "colorHex": "#F2F2F2",
          "backgroundColorHex": "#0D0D0D",
          "borderColorHex": "#333333"
        },
        "h1": {
          "color": "rgb(255, 255, 255)",
          "backgroundColor": "rgba(0, 0, 0, 0)",
          "backgroundImage": "none",
          "fontFamily": "Inter, \"Inter Fallback\"",
          "fontSize": "60px",
          "fontWeight": "800",
          "lineHeight": "60px",
          "letterSpacing": "normal",
          "borderColor": "rgb(51, 51, 51)",
          "borderWidth": "0px",
          "borderStyle": "solid",
          "borderRadius": "0px",
          "boxShadow": "none",
          "colorHex": "#FFFFFF",
          "backgroundColorHex": "#000000",
          "borderColorHex": "#333333"
        },
        "h2": {
          "color": "rgb(255, 255, 255)",
          "backgroundColor": "rgba(0, 0, 0, 0)",
          "backgroundImage": "none",
          "fontFamily": "Inter, \"Inter Fallback\"",
          "fontSize": "30px",
          "fontWeight": "700",
          "lineHeight": "36px",
          "letterSpacing": "normal",
          "borderColor": "rgb(51, 51, 51)",
          "borderWidth": "0px",
          "borderStyle": "solid",
          "borderRadius": "0px",
          "boxShadow": "none",
          "colorHex": "#FFFFFF",
          "backgroundColorHex": "#000000",
          "borderColorHex": "#333333"
        },
        "h3": {
          "color": "rgb(255, 255, 255)",
          "backgroundColor": "rgba(0, 0, 0, 0)",
          "backgroundImage": "none",
          "fontFamily": "Inter, \"Inter Fallback\"",
          "fontSize": "18px",
          "fontWeight": "600",
          "lineHeight": "28px",
          "letterSpacing": "normal",
          "borderColor": "rgb(51, 51, 51)",
          "borderWidth": "0px",
          "borderStyle": "solid",
          "borderRadius": "0px",
          "boxShadow": "none",
          "colorHex": "#FFFFFF",
          "backgroundColorHex": "#000000",
          "borderColorHex": "#333333"
        },
        "h4": {
          "color": "rgb(255, 255, 255)",
          "backgroundColor": "rgba(0, 0, 0, 0)",
          "backgroundImage": "none",
          "fontFamily": "Inter, \"Inter Fallback\"",
          "fontSize": "16px",
          "fontWeight": "600",
          "lineHeight": "24px",
          "letterSpacing": "normal",
          "borderColor": "rgb(51, 51, 51)",
          "borderWidth": "0px",
          "borderStyle": "solid",
          "borderRadius": "0px",
          "boxShadow": "none",
          "colorHex": "#FFFFFF",
          "backgroundColorHex": "#000000",
          "borderColorHex": "#333333"
        },
        "p": {
          "color": "rgb(209, 213, 219)",
          "backgroundColor": "rgba(0, 0, 0, 0)",
          "backgroundImage": "none",
          "fontFamily": "Inter, \"Inter Fallback\"",
          "fontSize": "20px",
          "fontWeight": "400",
          "lineHeight": "28px",
          "letterSpacing": "normal",
          "borderColor": "rgb(51, 51, 51)",
          "borderWidth": "0px",
          "borderStyle": "solid",
          "borderRadius": "0px",
          "boxShadow": "none",
          "colorHex": "#D1D5DB",
          "backgroundColorHex": "#000000",
          "borderColorHex": "#333333"
        },
        "a": {
          "color": "rgb(242, 242, 242)",
          "backgroundColor": "rgba(0, 0, 0, 0)",
          "backgroundImage": "none",
          "fontFamily": "Inter, \"Inter Fallback\"",
          "fontSize": "16px",
          "fontWeight": "400",
          "lineHeight": "24px",
          "letterSpacing": "normal",
          "borderColor": "rgb(51, 51, 51)",
          "borderWidth": "0px",
          "borderStyle": "solid",
          "borderRadius": "0px",
          "boxShadow": "none",
          "colorHex": "#F2F2F2",
          "backgroundColorHex": "#000000",
          "borderColorHex": "#333333"
        },
        "button": {
          "color": "rgb(242, 242, 242)",
          "backgroundColor": "rgba(0, 0, 0, 0)",
          "backgroundImage": "none",
          "fontFamily": "Inter, \"Inter Fallback\"",
          "fontSize": "14px",
          "fontWeight": "500",
          "lineHeight": "20px",
          "letterSpacing": "normal",
          "borderColor": "rgb(51, 51, 51)",
          "borderWidth": "0px",
          "borderStyle": "solid",
          "borderRadius": "0px",
          "boxShadow": "none",
          "colorHex": "#F2F2F2",
          "backgroundColorHex": "#000000",
          "borderColorHex": "#333333"
        },
        "nav": {
          "color": "rgb(242, 242, 242)",
          "backgroundColor": "rgba(0, 0, 0, 0)",
          "backgroundImage": "none",
          "fontFamily": "Inter, \"Inter Fallback\"",
          "fontSize": "16px",
          "fontWeight": "400",
          "lineHeight": "24px",
          "letterSpacing": "normal",
          "borderColor": "rgb(51, 51, 51)",
          "borderWidth": "0px",
          "borderStyle": "solid",
          "borderRadius": "0px",
          "boxShadow": "none",
          "colorHex": "#F2F2F2",
          "backgroundColorHex": "#000000",
          "borderColorHex": "#333333"
        },
        "card": {
          "color": "rgb(242, 242, 242)",
          "backgroundColor": "rgb(17, 24, 39)",
          "backgroundImage": "none",
          "fontFamily": "Inter, \"Inter Fallback\"",
          "fontSize": "16px",
          "fontWeight": "400",
          "lineHeight": "24px",
          "letterSpacing": "normal",
          "borderColor": "rgb(31, 41, 55)",
          "borderWidth": "1px",
          "borderStyle": "solid",
          "borderRadius": "12px",
          "boxShadow": "none",
          "colorHex": "#F2F2F2",
          "backgroundColorHex": "#111827",
          "borderColorHex": "#1F2937"
        },
        "brandText": {
          "color": "rgb(249, 116, 21)",
          "backgroundColor": "rgba(0, 0, 0, 0)",
          "backgroundImage": "none",
          "fontFamily": "Inter, \"Inter Fallback\"",
          "fontSize": "20px",
          "fontWeight": "700",
          "lineHeight": "28px",
          "letterSpacing": "normal",
          "borderColor": "rgb(51, 51, 51)",
          "borderWidth": "0px",
          "borderStyle": "solid",
          "borderRadius": "0px",
          "boxShadow": "none",
          "colorHex": "#F97415",
          "backgroundColorHex": "#000000",
          "borderColorHex": "#333333"
        },
        "brandBg": {
          "color": "rgb(255, 255, 255)",
          "backgroundColor": "rgb(249, 115, 22)",
          "backgroundImage": "none",
          "fontFamily": "Inter, \"Inter Fallback\"",
          "fontSize": "16px",
          "fontWeight": "600",
          "lineHeight": "24px",
          "letterSpacing": "normal",
          "borderColor": "rgb(51, 51, 51)",
          "borderWidth": "0px",
          "borderStyle": "solid",
          "borderRadius": "8px",
          "boxShadow": "none",
          "colorHex": "#FFFFFF",
          "backgroundColorHex": "#F97316",
          "borderColorHex": "#333333"
        },
        "gradient": {
          "color": "rgb(242, 242, 242)",
          "backgroundColor": "rgba(0, 0, 0, 0)",
          "backgroundImage": "linear-gradient(to right bottom, rgb(0, 0, 0), rgb(17, 24, 39), rgb(124, 45, 18))",
          "fontFamily": "Inter, \"Inter Fallback\"",
          "fontSize": "16px",
          "fontWeight": "400",
          "lineHeight": "24px",
          "letterSpacing": "normal",
          "borderColor": "rgb(51, 51, 51)",
          "borderWidth": "0px",
          "borderStyle": "solid",
          "borderRadius": "0px",
          "boxShadow": "none",
          "colorHex": "#F2F2F2",
          "backgroundColorHex": "#000000",
          "borderColorHex": "#333333"
        }
      },
      "screenshot": "reports/theme-audit/before/why-utah.png"
    },
    {
      "url": "http://localhost:3000/",
      "label": "home",
      "styles": {
        "body": {
          "color": "rgb(0, 0, 0)",
          "backgroundColor": "rgb(255, 255, 255)",
          "backgroundImage": "none",
          "fontFamily": "Inter, \"Inter Fallback\"",
          "fontSize": "16px",
          "fontWeight": "400",
          "lineHeight": "24px",
          "letterSpacing": "normal",
          "borderColor": "rgb(229, 229, 229)",
          "borderWidth": "0px",
          "borderStyle": "solid",
          "borderRadius": "0px",
          "boxShadow": "none",
          "colorHex": "#000000",
          "backgroundColorHex": "#FFFFFF",
          "borderColorHex": "#E5E5E5"
        },
        "h1": {
          "color": "rgb(255, 255, 255)",
          "backgroundColor": "rgba(0, 0, 0, 0)",
          "backgroundImage": "none",
          "fontFamily": "Inter, \"Inter Fallback\"",
          "fontSize": "60px",
          "fontWeight": "800",
          "lineHeight": "60px",
          "letterSpacing": "-1.5px",
          "borderColor": "rgb(229, 229, 229)",
          "borderWidth": "0px",
          "borderStyle": "solid",
          "borderRadius": "0px",
          "boxShadow": "none",
          "colorHex": "#FFFFFF",
          "backgroundColorHex": "#000000",
          "borderColorHex": "#E5E5E5"
        },
        "h2": {
          "color": "rgb(0, 0, 0)",
          "backgroundColor": "rgba(0, 0, 0, 0)",
          "backgroundImage": "none",
          "fontFamily": "Inter, \"Inter Fallback\"",
          "fontSize": "30px",
          "fontWeight": "700",
          "lineHeight": "36px",
          "letterSpacing": "normal",
          "borderColor": "rgb(229, 229, 229)",
          "borderWidth": "0px",
          "borderStyle": "solid",
          "borderRadius": "0px",
          "boxShadow": "none",
          "colorHex": "#000000",
          "backgroundColorHex": "#000000",
          "borderColorHex": "#E5E5E5"
        },
        "h3": {
          "color": "rgb(0, 0, 0)",
          "backgroundColor": "rgba(0, 0, 0, 0)",
          "backgroundImage": "none",
          "fontFamily": "Inter, \"Inter Fallback\"",
          "fontSize": "20px",
          "fontWeight": "600",
          "lineHeight": "28px",
          "letterSpacing": "normal",
          "borderColor": "rgb(229, 229, 229)",
          "borderWidth": "0px",
          "borderStyle": "solid",
          "borderRadius": "0px",
          "boxShadow": "none",
          "colorHex": "#000000",
          "backgroundColorHex": "#000000",
          "borderColorHex": "#E5E5E5"
        },
        "p": {
          "color": "rgb(209, 213, 219)",
          "backgroundColor": "rgba(0, 0, 0, 0)",
          "backgroundImage": "none",
          "fontFamily": "Inter, \"Inter Fallback\"",
          "fontSize": "20px",
          "fontWeight": "400",
          "lineHeight": "28px",
          "letterSpacing": "normal",
          "borderColor": "rgb(229, 229, 229)",
          "borderWidth": "0px",
          "borderStyle": "solid",
          "borderRadius": "0px",
          "boxShadow": "none",
          "colorHex": "#D1D5DB",
          "backgroundColorHex": "#000000",
          "borderColorHex": "#E5E5E5"
        },
        "a": {
          "color": "rgb(0, 0, 0)",
          "backgroundColor": "rgba(0, 0, 0, 0)",
          "backgroundImage": "none",
          "fontFamily": "Inter, \"Inter Fallback\"",
          "fontSize": "16px",
          "fontWeight": "400",
          "lineHeight": "24px",
          "letterSpacing": "normal",
          "borderColor": "rgb(229, 229, 229)",
          "borderWidth": "0px",
          "borderStyle": "solid",
          "borderRadius": "0px",
          "boxShadow": "none",
          "colorHex": "#000000",
          "backgroundColorHex": "#000000",
          "borderColorHex": "#E5E5E5"
        },
        "button": {
          "color": "rgb(0, 0, 0)",
          "backgroundColor": "rgba(0, 0, 0, 0)",
          "backgroundImage": "none",
          "fontFamily": "Inter, \"Inter Fallback\"",
          "fontSize": "14px",
          "fontWeight": "500",
          "lineHeight": "20px",
          "letterSpacing": "normal",
          "borderColor": "rgb(229, 229, 229)",
          "borderWidth": "0px",
          "borderStyle": "solid",
          "borderRadius": "0px",
          "boxShadow": "none",
          "colorHex": "#000000",
          "backgroundColorHex": "#000000",
          "borderColorHex": "#E5E5E5"
        },
        "input": {
          "color": "rgb(0, 0, 0)",
          "backgroundColor": "rgb(255, 255, 255)",
          "backgroundImage": "none",
          "fontFamily": "Inter, \"Inter Fallback\"",
          "fontSize": "14px",
          "fontWeight": "400",
          "lineHeight": "20px",
          "letterSpacing": "normal",
          "borderColor": "rgb(229, 229, 229)",
          "borderWidth": "1px",
          "borderStyle": "solid",
          "borderRadius": "6px",
          "boxShadow": "none",
          "colorHex": "#000000",
          "backgroundColorHex": "#FFFFFF",
          "borderColorHex": "#E5E5E5"
        },
        "nav": {
          "color": "rgb(0, 0, 0)",
          "backgroundColor": "rgba(0, 0, 0, 0)",
          "backgroundImage": "none",
          "fontFamily": "Inter, \"Inter Fallback\"",
          "fontSize": "16px",
          "fontWeight": "400",
          "lineHeight": "24px",
          "letterSpacing": "normal",
          "borderColor": "rgb(229, 229, 229)",
          "borderWidth": "0px",
          "borderStyle": "solid",
          "borderRadius": "0px",
          "boxShadow": "none",
          "colorHex": "#000000",
          "backgroundColorHex": "#000000",
          "borderColorHex": "#E5E5E5"
        },
        "card": {
          "color": "rgb(255, 255, 255)",
          "backgroundColor": "rgb(17, 24, 39)",
          "backgroundImage": "none",
          "fontFamily": "Inter, \"Inter Fallback\"",
          "fontSize": "16px",
          "fontWeight": "400",
          "lineHeight": "24px",
          "letterSpacing": "normal",
          "borderColor": "rgb(229, 229, 229)",
          "borderWidth": "0px",
          "borderStyle": "solid",
          "borderRadius": "0px",
          "boxShadow": "none",
          "colorHex": "#FFFFFF",
          "backgroundColorHex": "#111827",
          "borderColorHex": "#E5E5E5"
        },
        "brandText": {
          "color": "rgb(255, 119, 0)",
          "backgroundColor": "rgba(0, 0, 0, 0)",
          "backgroundImage": "none",
          "fontFamily": "Inter, \"Inter Fallback\"",
          "fontSize": "20px",
          "fontWeight": "700",
          "lineHeight": "28px",
          "letterSpacing": "normal",
          "borderColor": "rgb(229, 229, 229)",
          "borderWidth": "0px",
          "borderStyle": "solid",
          "borderRadius": "0px",
          "boxShadow": "none",
          "colorHex": "#FF7700",
          "backgroundColorHex": "#000000",
          "borderColorHex": "#E5E5E5"
        },
        "brandBg": {
          "color": "rgb(255, 255, 255)",
          "backgroundColor": "rgb(255, 119, 0)",
          "backgroundImage": "none",
          "fontFamily": "Inter, \"Inter Fallback\"",
          "fontSize": "14px",
          "fontWeight": "500",
          "lineHeight": "20px",
          "letterSpacing": "normal",
          "borderColor": "rgb(229, 229, 229)",
          "borderWidth": "0px",
          "borderStyle": "solid",
          "borderRadius": "6px",
          "boxShadow": "none",
          "colorHex": "#FFFFFF",
          "backgroundColorHex": "#FF7700",
          "borderColorHex": "#E5E5E5"
        },
        "gradient": {
          "color": "rgb(0, 0, 0)",
          "backgroundColor": "rgba(0, 0, 0, 0)",
          "backgroundImage": "linear-gradient(to right, rgb(17, 24, 39), rgb(31, 41, 55))",
          "fontFamily": "Inter, \"Inter Fallback\"",
          "fontSize": "16px",
          "fontWeight": "400",
          "lineHeight": "24px",
          "letterSpacing": "normal",
          "borderColor": "rgb(229, 229, 229)",
          "borderWidth": "0px",
          "borderStyle": "solid",
          "borderRadius": "0px",
          "boxShadow": "none",
          "colorHex": "#000000",
          "backgroundColorHex": "#000000",
          "borderColorHex": "#E5E5E5"
        }
      },
      "screenshot": "reports/theme-audit/before/home.png"
    },
    {
      "url": "http://localhost:3000/dashboard",
      "label": "dashboard",
      "styles": {
        "body": {
          "color": "rgb(242, 242, 242)",
          "backgroundColor": "rgb(13, 13, 13)",
          "backgroundImage": "none",
          "fontFamily": "Inter, \"Inter Fallback\"",
          "fontSize": "16px",
          "fontWeight": "400",
          "lineHeight": "24px",
          "letterSpacing": "normal",
          "borderColor": "rgb(51, 51, 51)",
          "borderWidth": "0px",
          "borderStyle": "solid",
          "borderRadius": "0px",
          "boxShadow": "none",
          "colorHex": "#F2F2F2",
          "backgroundColorHex": "#0D0D0D",
          "borderColorHex": "#333333"
        },
        "h1": {
          "color": "rgb(242, 242, 242)",
          "backgroundColor": "rgba(0, 0, 0, 0)",
          "backgroundImage": "none",
          "fontFamily": "Inter, \"Inter Fallback\"",
          "fontSize": "36px",
          "fontWeight": "700",
          "lineHeight": "40px",
          "letterSpacing": "normal",
          "borderColor": "rgb(51, 51, 51)",
          "borderWidth": "0px",
          "borderStyle": "solid",
          "borderRadius": "0px",
          "boxShadow": "none",
          "colorHex": "#F2F2F2",
          "backgroundColorHex": "#000000",
          "borderColorHex": "#333333"
        },
        "h3": {
          "color": "rgb(255, 255, 255)",
          "backgroundColor": "rgba(0, 0, 0, 0)",
          "backgroundImage": "none",
          "fontFamily": "Inter, \"Inter Fallback\"",
          "fontSize": "18px",
          "fontWeight": "600",
          "lineHeight": "28px",
          "letterSpacing": "normal",
          "borderColor": "rgb(51, 51, 51)",
          "borderWidth": "0px",
          "borderStyle": "solid",
          "borderRadius": "0px",
          "boxShadow": "none",
          "colorHex": "#FFFFFF",
          "backgroundColorHex": "#000000",
          "borderColorHex": "#333333"
        },
        "p": {
          "color": "rgb(191, 191, 191)",
          "backgroundColor": "rgba(0, 0, 0, 0)",
          "backgroundImage": "none",
          "fontFamily": "Inter, \"Inter Fallback\"",
          "fontSize": "18px",
          "fontWeight": "400",
          "lineHeight": "28px",
          "letterSpacing": "normal",
          "borderColor": "rgb(51, 51, 51)",
          "borderWidth": "0px",
          "borderStyle": "solid",
          "borderRadius": "0px",
          "boxShadow": "none",
          "colorHex": "#BFBFBF",
          "backgroundColorHex": "#000000",
          "borderColorHex": "#333333"
        },
        "a": {
          "color": "rgb(242, 242, 242)",
          "backgroundColor": "rgba(0, 0, 0, 0)",
          "backgroundImage": "none",
          "fontFamily": "Inter, \"Inter Fallback\"",
          "fontSize": "16px",
          "fontWeight": "400",
          "lineHeight": "24px",
          "letterSpacing": "normal",
          "borderColor": "rgb(51, 51, 51)",
          "borderWidth": "0px",
          "borderStyle": "solid",
          "borderRadius": "0px",
          "boxShadow": "none",
          "colorHex": "#F2F2F2",
          "backgroundColorHex": "#000000",
          "borderColorHex": "#333333"
        },
        "button": {
          "color": "rgb(242, 242, 242)",
          "backgroundColor": "rgba(0, 0, 0, 0)",
          "backgroundImage": "none",
          "fontFamily": "Inter, \"Inter Fallback\"",
          "fontSize": "14px",
          "fontWeight": "500",
          "lineHeight": "20px",
          "letterSpacing": "normal",
          "borderColor": "rgb(51, 51, 51)",
          "borderWidth": "0px",
          "borderStyle": "solid",
          "borderRadius": "0px",
          "boxShadow": "none",
          "colorHex": "#F2F2F2",
          "backgroundColorHex": "#000000",
          "borderColorHex": "#333333"
        },
        "nav": {
          "color": "rgb(242, 242, 242)",
          "backgroundColor": "rgba(0, 0, 0, 0)",
          "backgroundImage": "none",
          "fontFamily": "Inter, \"Inter Fallback\"",
          "fontSize": "16px",
          "fontWeight": "400",
          "lineHeight": "24px",
          "letterSpacing": "normal",
          "borderColor": "rgb(51, 51, 51)",
          "borderWidth": "0px",
          "borderStyle": "solid",
          "borderRadius": "0px",
          "boxShadow": "none",
          "colorHex": "#F2F2F2",
          "backgroundColorHex": "#000000",
          "borderColorHex": "#333333"
        },
        "card": {
          "color": "rgb(255, 255, 255)",
          "backgroundColor": "rgb(17, 24, 39)",
          "backgroundImage": "none",
          "fontFamily": "Inter, \"Inter Fallback\"",
          "fontSize": "16px",
          "fontWeight": "400",
          "lineHeight": "24px",
          "letterSpacing": "normal",
          "borderColor": "rgb(51, 51, 51)",
          "borderWidth": "0px",
          "borderStyle": "solid",
          "borderRadius": "0px",
          "boxShadow": "none",
          "colorHex": "#FFFFFF",
          "backgroundColorHex": "#111827",
          "borderColorHex": "#333333"
        },
        "brandText": {
          "color": "rgb(249, 116, 21)",
          "backgroundColor": "rgba(0, 0, 0, 0)",
          "backgroundImage": "none",
          "fontFamily": "Inter, \"Inter Fallback\"",
          "fontSize": "20px",
          "fontWeight": "700",
          "lineHeight": "28px",
          "letterSpacing": "normal",
          "borderColor": "rgb(51, 51, 51)",
          "borderWidth": "0px",
          "borderStyle": "solid",
          "borderRadius": "0px",
          "boxShadow": "none",
          "colorHex": "#F97415",
          "backgroundColorHex": "#000000",
          "borderColorHex": "#333333"
        }
      },
      "screenshot": "reports/theme-audit/before/dashboard.png"
    }
  ]
}